{
    "en_US": {
        "CET矿池": "CET矿池",
        "周边商城": "周边商城",
        "海坡语录": "Haipo words",
        "论坛@DEPRECATED@": "Forum",
        "购买CET": "Get CET",
        "资料库": "Docs"
    },
    "zh_Hans_CN": {
        "CET矿池": "CET矿池",
        "周边商城": "周边商城",
        "海坡语录": "海坡语录",
        "购买CET": "购买CET",
        "资料库": "资料库"
    },
    "zh_Hant_HK": {
        "CET矿池": "CET礦池",
        "周边商城": "周邊商城",
        "海坡语录": "海坡語錄",
        "论坛@DEPRECATED@": "論壇",
        "购买CET": "購買CET",
        "资料库": "資料庫"
    }
}